asyncflow.py
asyncflow-0.1.dist-info/LICENSE
asyncflow-0.1.dist-info/METADATA
asyncflow-0.1.dist-info/WHEEL
asyncflow-0.1.dist-info/top_level.txt
asyncflow-0.1.dist-info/RECORD
